dash_selectable/DashSelectable.py
dash_selectable/__init__.py
dash_selectable/_imports_.py
dash_selectable/dash_selectable.min.js
dash_selectable/dash_selectable.min.js.map
dash_selectable/metadata.json
dash_selectable/package-info.json
dash_selectable-0.0.1.dist-info/LICENSE
dash_selectable-0.0.1.dist-info/METADATA
dash_selectable-0.0.1.dist-info/WHEEL
dash_selectable-0.0.1.dist-info/top_level.txt
dash_selectable-0.0.1.dist-info/RECORD
